faststr/Segmented_Global_Alignment.py
faststr/__init__.py
faststr/get_subread_trs.py
faststr/main.py
faststr/make_consensus_TRs.py
faststr/scan_subread.py
faststr/trs_align.py
faststr/utils.py
faststr-1.0.0.dist-info/METADATA
faststr-1.0.0.dist-info/WHEEL
faststr-1.0.0.dist-info/entry_points.txt
faststr-1.0.0.dist-info/top_level.txt
faststr-1.0.0.dist-info/RECORD
