Metadata-Version: 2.4
Name: FastSTR
Version: 1.0.0
Summary: FastSTR: A high-performance tool for short tandem repeat (STR) detection and analysis from genome assemblies.
Author-email: Wen Long <wenlong2024@mail.nwpu.edu.cn>
Maintainer-email: Wen Long <wenlong2024@mail.nwpu.edu.cn>
License-Expression: MIT
Project-URL: Homepage, https://github.com/XL-BioGroup/FastSTR
Project-URL: Repository, https://github.com/XL-BioGroup/FastSTR
Project-URL: Issues, https://github.com/XL-BioGroup/FastSTR/issues
Keywords: tandem repeat,STR,genome,bioinformatics,sequence alignment
Classifier: Development Status :: 5 - Production/Stable
Classifier: Intended Audience :: Science/Research
Classifier: Topic :: Scientific/Engineering :: Bio-Informatics
Classifier: Programming Language :: Python :: 3.9
Classifier: Operating System :: OS Independent
Requires-Python: >=3.9
Requires-Dist: biopython==1.83
Requires-Dist: numpy==1.26.0
Requires-Dist: pandas==2.2.2
Requires-Dist: regex==2024.9.11
Requires-Dist: scikit-learn==1.5.2
